mthd/__init__.py
mthd-0.0.2.dist-info/METADATA
mthd-0.0.2.dist-info/WHEEL
mthd-0.0.2.dist-info/licenses/LICENSE
mthd-0.0.2.dist-info/RECORD
